LordXen/__init__.py
LordXen/exceptions.py
LordXen-2023.7.23.dist-info/METADATA
LordXen-2023.7.23.dist-info/WHEEL
LordXen-2023.7.23.dist-info/top_level.txt
LordXen-2023.7.23.dist-info/RECORD
