Metadata-Version: 2.1
Name: LordXen
Version: 2023.7.23
Summary: Python XenForo Api Lib für Posten 
Author-email: lordbex <lordibex@protonmail.com>
Maintainer-email: lordbex <lordibex@protonmail.com>
Project-URL: homepage, https://github.com/LordBex/LordXen
Project-URL: repository, https://github.com/LordBex/LordXen
Requires-Python: >=3.10
